odoo/addons/website_sale_product_reference_displayed/README.rst
odoo/addons/website_sale_product_reference_displayed/__init__.py
odoo/addons/website_sale_product_reference_displayed/__manifest__.py
odoo/addons/website_sale_product_reference_displayed/data/snippet_filter_data.xml
odoo/addons/website_sale_product_reference_displayed/i18n/ca.po
odoo/addons/website_sale_product_reference_displayed/i18n/es.po
odoo/addons/website_sale_product_reference_displayed/i18n/fr.po
odoo/addons/website_sale_product_reference_displayed/i18n/it.po
odoo/addons/website_sale_product_reference_displayed/i18n/pt_BR.po
odoo/addons/website_sale_product_reference_displayed/i18n/website_sale_product_reference_displayed.pot
odoo/addons/website_sale_product_reference_displayed/models/__init__.py
odoo/addons/website_sale_product_reference_displayed/models/website_snippet_filter.py
odoo/addons/website_sale_product_reference_displayed/readme/CONTRIBUTORS.md
odoo/addons/website_sale_product_reference_displayed/readme/DESCRIPTION.md
odoo/addons/website_sale_product_reference_displayed/readme/USAGE.md
odoo/addons/website_sale_product_reference_displayed/static/description/enable-product-reference.png
odoo/addons/website_sale_product_reference_displayed/static/description/icon.png
odoo/addons/website_sale_product_reference_displayed/static/description/index.html
odoo/addons/website_sale_product_reference_displayed/views/website_sale_views.xml
odoo_addon_website_sale_product_reference_displayed-18.0.1.0.0.3.dist-info/METADATA
odoo_addon_website_sale_product_reference_displayed-18.0.1.0.0.3.dist-info/WHEEL
odoo_addon_website_sale_product_reference_displayed-18.0.1.0.0.3.dist-info/top_level.txt
odoo_addon_website_sale_product_reference_displayed-18.0.1.0.0.3.dist-info/RECORD
